Workbook

Sheet GuideGestion
B1: Nom de la Cuma | C1: CUMA DE TEST | G1: 999003
B2: Numéro de gestion | C2: TEST999001 | G2: 999356
B3: Commune | C3: PARIS
B4: Numéro d'agrément | C4: AGR999001 | G4: 999001
B5: Cloture N | G5: 75
B6: Cloture N-1 | C6: clot | G6: GDROOT
B7: Cloture N-2 | C7: clot | G7: Guide gestion
B8: Nom Comptable | C8: Ali BABA
B9: Tel Comptable | C9: 01.02.03.04.05
B10: mail comptable | C10: ali.baba@Cuma.fr
B11: nb_adh | C11: 64
A12: datedebut | C12: 01/01/2025 | D12: 01/01/2024 | E12: 01/01/2023 | F12: 01/01/2022
A13: datefin | C13: 31/12/2025 | D13: 31/12/2024 | E13: 31/12/2023 | F13: 31/12/2022
B14: DIFFERENTS NIVEAUX DE RESULTATS
A15: compte=(7-71) | B15: Chiffre d'affaires | C15: 562308.95 | D15: 500655.03 | E15: 517570.12 | F15: 418996.4
A16: compte=(70;74-746;748-749;60;61;62;63;64) | B16: Excédent brut d'exploitation | C16: 235445.07 | D16: 223675.74 | E16: 261796.64 | F16: 207917.37
A17: Compte=(6-66;68-686;688-689;7-76;78-786;788-79) | B17: Résultat courant | C17: 234249.79 | D17: -1379.57 | E17: 64422.42 | F17: 16236.84
A18: Compte=(695) | B18: Résultat IS | C18: 0 | D18: 0 | E18: 0 | F18: 0
A19: Compte=(67;687;69-694;696-699;77;787) | B19: Résultat exceptionnel | C19: 118480.12 | D19: 11409.29 | E19: 27443.23 | F19: -29391.43
B20: Résultat Net Comptable | C20: =C17+C19+C18 -> 352729.91 | D20: =D17+D19+D18 -> 10029.72 | E20: =E17+E19+E18 -> 91865.65 | F20: =F17+F19+F18 -> -13154.59
B21: ANALYSE DES CHARGES DE LA CUMA
A22: Compte=(70-7062;7064-708;709-71) | B22: Chiffre d'affaires corrigé | C22: 562308.95 | D22: 500655.03 | E22: 517570.12 | F22: 418996.4
A23: Compte=(70612010;70612020;70613010;70613020;70617010;70617020;70618010;70618020;70620010;70620020;70630010;70630020;70830010;70830020) | B23: CA Taux reduit | C23: 291429.01 | D23: 267485.71 | E23: 270858.68 | F23: 185654.28
A24: Compte=(6063;60211;603211;60223;60322;615;7581;7587;7912) credit=negatif | B24: Entretien réparation corrigé | C24: 93716.75 | D24: 80962.24 | E24: 68307.68 | F24: 63996.28
B25: Entretien réparation corrigé / CA corrigé | C25: =IF(C22=0,0,C24/C22*100) -> 16.666416 | D25: =IF(D22=0,0,D24/D22*100) -> 16.171263 | E25: =IF(E22=0,0,E24/E22*100) -> 13.197763 | F25: =IF(F22=0,0,F24/F22*100) -> 15.273706
A26: Compte=(6811;6816) credit=negatif | B26: Amortissement | C26: 0 | D26: 187408.12 | E26: 178752.87 | F26: 169664.89
B27: Amortissement / CA corrigé | C27: =IF(C22=0,0,C26/C22*100) -> 0 | D27: =IF(D22=0,0,D26/D22*100) -> 37.432585 | E27: =IF(E22=0,0,E26/E22*100) -> 34.536938 | F27: =IF(F22=0,0,F26/F22*100) -> 40.493162
A28: Compte=(64) credit=negatif | B28: Charges salariales | C28: 67728.85 | D28: 32405.75 | E28: 36312.8 | F28: 32604.53
B29: Charges salariales / CA corrigé | C29: =IF(C22=0,0,C28/C22*100) -> 12.044775 | D29: =IF(GuideGestion!D22=0,0,D28/GuideGestion!D22*100) -> 6.4726704 | E29: =IF(GuideGestion!E22=0,0,E28/GuideGestion!E22*100) -> 7.0160155 | F29: =IF(GuideGestion!F22=0,0,F28/GuideGestion!F22*100) -> 7.7815776
A30: Compte=(60212;603212) credit=negatif | B30: Carburant | C30: 65706.47 | D30: 60001.4 | E30: 78623.72 | F30: 66412.52
A31: Compte=(66) credit=negatif | B31: Frais financier | C31: 25126.49 | D31: 25599.09 | E31: 19672.66 | F31: 12972.81
B32: Frais financier / CA corrigé | C32: =IF(C22=0,0,C31/C22*100) -> 4.4684492 | D32: =IF(GuideGestion!D22=0,0,D31/GuideGestion!D22*100) -> 5.1131195 | E32: =IF(GuideGestion!E22=0,0,E31/GuideGestion!E22*100) -> 3.8009652 | F32: =IF(GuideGestion!F22=0,0,F31/GuideGestion!F22*100) -> 3.0961626
B33: FINANCEMENT DE L'EXERCICE
A34: Compte=(6-656;658-674;676-756;758-774;776-79) credit=positif | B34: Résultat (hors vente matériel) | C34: 201729.91 | D34: 122.12 | E34: 64426.84 | F34: 16236.84
A35: Compte=(68) credit=negatif | B35: Dotation Amort+prov | C35: 0 | D35: 187487.67 | E35: 178752.87 | F35: 171832.73
A36: Compte=(747;777;781;787) credit=positif | B36: Dotation rep/prov | C36: 0 | D36: 790.39 | E36: 11561.63 | F36: 0
B37: Dotation Amort+prov – rep/prov | C37: =C35-C36 -> 0 | D37: =D35-D36 -> 186697.28 | E37: =E35-E36 -> 167191.24 | F37: =F35-F36 -> 171832.73
A38: critere | C38: DB | D38: DB | E38: DB | F38: DB
A39: Compte=(8168) credit=negatif | B39: Emprunt remboursé par anticipation | C39: 0 | D39: 0 | E39: 0 | F39: 139125.55
A40: Compte=(164-16400;16402-16410;16412-16420;16422-16430;16432-16440;16442-16450;16452-16460;16462-16470;16472-16479;16482-16490;16492-16499;162) | B40: Remboursement du cap des emprunts long et moyen terme de l'année | C40: 311005.33 | D40: 223791.05 | E40: 305674.89 | F40: 326325.96
B41: Remboursement du cap des emprunts long et moyen terme de l'année | C41: =C40-C39 -> 311005.33 | D41: =D40-D39 -> 223791.05 | E41: =E40-E39 -> 305674.89 | F41: =F40-F39 -> 187200.41
A42: Compte=(21;23) | B42: Achat d'immo | C42: 600907.92 | D42: 143350 | E42: 387150 | F42: 757921
A43: Compte=(21) | B43: Achat d'immo sans acomptes | C43: 574657.92 | D43: 143350 | E43: 387150 | F43: 757921
B44: Capacité d'Autofinancement Net | C44: =C34+C37-C41 -> -109275.42 | D44: =D34+D37-D41 -> -36971.65 | E44: =E34+E37-E41 -> -74056.81 | F44: =F34+F37-F41 -> 869.16
A45: Compte=(8453) | B45: Créances à plus d'un an | C45: 0 | D45: 25500.34 | E45: 10108.65 | F45: 23474.46
A46: critere | C46: SO | D46: SO | E46: SO | F46: SO
A47: Compte=(2715;26) | B47: Augmentation PS | C47: 68.85 | D47: 115.79 | E47: 44.37 | F47: 36.72
A48: Compte=(775;757) credit=positif | B48: Revente d'immo | C48: 151000 | D48: 12000 | E48: 158300 | F48: 253000
A49: compte=(657;757) credit=positif | B49: plu ou moins value | C49: 32500 | D49: 0 | E49: 0 | F49: 0
A50: Compte=(1012-1013) | B50: Variation capital | C50: 0 | D50: 10290 | E50: 5200 | F50: -324
A51: critere | C51: CR | D51: CR | E51: CR | F51: CR
A52: Compte=(164-16400;16402-16410;16412-16420;16422-16430;16432-16440;16442-16450;16452-16460;16462-16470;16472-16479;16482-16490;16492-16499;162) | B52: Réalisation d'emprunt LMT | C52: 566600 | D52: 112400 | E52: 779573.22 | F52: 61407
A53: Compte=(131;138-139;10621) | B53: Subvention | C53: 0 | D53: 8439 | E53: 0 | F53: 0
A54: Compte=(8164) | B54: Emprunt à recevoir | C54: 0 | D54: 0 | E54: 0 | F54: 409000
B55: Besoin d'autofinancement | C55: =C42+C47-C52-C48-C50-C53+C39 -> -116623.23 | D55: =D42+D47-D52-D48-D50-D53+D39 -> 336.79 | E55: =E42+E47-E52-E48-E50-E53+E39 -> -555878.85 | F55: =F42+F47-F52-F48-F50-F53+F39 -> 583000.27
A56: critere | C56: SO | D56: SO | E56: SO | F56: SO
A57: Compte=(68174) | B57: variation du fonds de roulement | C57: 0 | D57: -79.55 | E57: 0 | F57: -2167.84
A58: Compte=(78174) | B58: variation du fonds de roulement | C58: 0 | D58: 0 | E58: 11561.63 | F58: 0
B59: variation du fonds de roulement | C59: =C57+C58 -> 0 | D59: =D57+D58 -> -79.55 | E59: =E57+E58 -> 11561.63 | F59: =F57+F58 -> -2167.84
B60: Variation fond de roulement | C60: =C44-C55+C59 -> 7347.81 | D60: =GuideGestion!D44-GuideGestion!D55+D59 -> -37387.99 | E60: =GuideGestion!E44-GuideGestion!E55+E59 -> 493383.67 | F60: =GuideGestion!F44-GuideGestion!F55+F59 -> -584298.95
A61: critere | C61: SO | D61: SO | E61: SO | F61: SO
A62: datedebut | C62: 01/01/2000 | D62: 01/01/2000 | E62: 01/01/2000 | F62: 01/01/2000
A63: Compte=(2815) credit=negatif | B63: montants amorti | C63: -927922.27 | D63: -927922.27 | E63: -758056.35 | F63: -749628.66
A64: Compte=(215)credit=positif | B64: montant total des immos | C64: -3057835.5 | D64: -2483177.6 | E64: -2358576.1 | F64: -2274273.4
B65: Taux de vétusté | C65: =IF(C64=0,0,C63/C64)*100 -> 30.345722 | D65: =IF(D64=0,0,D63/D64)*100 -> 37.368341 | E65: =IF(E64=0,0,E63/E64)*100 -> 32.140424 | F65: =IF(F64=0,0,F63/F64)*100 -> 32.961238
B66: FONDS DE ROULEMENT DE DISPONIBILITE
A67: critere | C67: SD | D67: SD | E67: SD | F67: SD
A68: Compte=(48-485;487-489) credit=negatif | B68: Comptes de régularisation sans charges constatées d'avance | C68: 0 | D68: 0 | E68: 0 | F68: 0
A69: critere | C69: SO | D69: SO | E69: SO | F69: SO
A70: Compte=(10-15;162;164;2) credit=positif | B70: Capital et réserves sans résultat | C70: 32275.89 | D70: 310517.99 | E70: 379305.98 | F70: -134552.69
B71: Capital et réserves avec résultat | C71: =C70+IF(GuideGestion!C5="",C20,0) -> 385005.8 | D71: =D70+IF(GuideGestion!C6="",GuideGestion!D20,0) -> 310517.99 | E71: =E70+IF(GuideGestion!C7="",GuideGestion!E20,0) -> 379305.98 | F71: =F70+IF(GuideGestion!D7="",GuideGestion!F20,0) -> -147707.28
A72: Compte=(15) | B72: Provisions pour risques et charges | C72: 0 | D72: 0 | E72: 0 | F72: 0
A73: Compte=(16401;16411;16421;16431;16441;16451;16461;16471;16480;16481;16491) credit=positif | B73: sauf emprunts CT | C73: 89620 | D73: 22480 | E73: 53880 | F73: 36105
B74: Fond de roulement | C74: =(C71+C68-C73) -> 295385.8 | D74: =(D71+D68-D73) -> 288037.99 | E74: =(E71+E68-E73) -> 325425.98 | F74: =(F71+F68-F73) -> -183812.28
B75: Fond de roulement / CA | C75: =IF(C15=0,0,C74/C15*100) -> 52.530873 | D75: =IF(GuideGestion!D15=0,0,D74/GuideGestion!D15*100) -> 57.532227 | E75: =IF(GuideGestion!E15=0,0,E74/GuideGestion!E15*100) -> 62.875728 | F75: =IF(GuideGestion!F15=0,0,F74/GuideGestion!F15*100) -> -43.869656
A76: Compte=(32;34;375;4091;50;53;54;486)credit=negatif | B76: Actif circulant (parties en SO) | C76: 2274.34 | D76: 2274.34 | E76: 5182.4 | F76: 4574.16
A77: critere | C77: SO | D77: SO | E77: SO | F77: SO
A78: Compte=(40-4090;4092-4099;41-4190;4192-450;452-4759;477-479;51-518)credit=negatif | B78: Actif circulant (parties en TD) | C78: 401277.26 | D78: 326789.45 | E78: 391811.28 | F78: 173.31
A79: Compte=(453) credit=negatif | B79: Créances TTC | C79: 103761.18 | D79: 120742.22 | E79: 145738.86 | F79: 119940.67
B80: Créances / CA | C80: =IF(C15=0,0,C79/C15*100) -> 18.452699 | D80: =IF(GuideGestion!D15=0,0,D79/GuideGestion!D15*100) -> 24.116849 | E80: =IF(GuideGestion!E15=0,0,E79/GuideGestion!E15*100) -> 28.158283 | F80: =IF(GuideGestion!F15=0,0,F79/GuideGestion!F15*100) -> 28.625704
B81: Trésorerie Nette Globale
B82: CAPITAL SOCIAL – recours à l'emprunt
A83: critere | C83: SO | D83: SO | E83: SO | F83: SO
A84: Compte=(101) credit=positif | B84: CS | C84: 150862 | D84: 150862 | E84: 140572 | F84: 135372
B85: CS / CA | C85: =IF(C15=0,0,C84/C15*100) -> 26.829023 | D85: =IF(GuideGestion!D15=0,0,D84/GuideGestion!D15*100) -> 30.132924 | E85: =IF(GuideGestion!E15=0,0,E84/GuideGestion!E15*100) -> 27.159991 | F85: =IF(GuideGestion!F15=0,0,F84/GuideGestion!F15*100) -> 32.308631
A86: Compte=(215) credit=negatif | B86: Valeur brute matériel | C86: 3057835.5 | D86: 2483177.6 | E86: 2358576.1 | F86: 2274273.4
A87: Compte=(21) credit=negatif | B87: Valeur brute immobilisé | C87: 3104775 | D87: 2530117.1 | E87: 2405515.6 | F87: 2321212.9
B88: CS / Valeur brute matériel | C88: =IF(C86=0,0,C84/C86*100) -> 4.9336205 | D88: =IF(D86=0,0,D84/D86*100) -> 6.0753609 | E88: =IF(E86=0,0,E84/E86*100) -> 5.9600367 | F88: =IF(F86=0,0,F84/F86*100) -> 5.9523187
A89: Compte=(10-14) credit=positif | B89: Capitaux propres sans résultat | C89: 729211.49 | D89: 729211.49 | E89: 701243.16 | F89: 604177.51
B90: Capitaux propres avec résultat | C90: =C89+IF(GuideGestion!C5="",C20,0) -> 1081941.4 | D90: =D89+IF(GuideGestion!C6="",GuideGestion!D20,0) -> 729211.49 | E90: =E89+IF(GuideGestion!C7="",GuideGestion!E20,0) -> 701243.16 | F90: =F89+IF(GuideGestion!D7="",GuideGestion!F20,0) -> 591022.92
B91: CS / Capitaux propres | C91: =IF(C90=0,0,C84/C90*100) -> 13.943639 | D91: =IF(D90=0,0,D84/D90*100) -> 20.688374 | E91: =IF(E90=0,0,E84/E90*100) -> 20.046114 | F91: =IF(F90=0,0,F84/F90*100) -> 22.904695
B92: Entretien / Valeur brute matériel | C92: =IF(C86=0,0,C24/C86*100) -> 3.0648068 | D92: =IF(D86=0,0,D24/D86*100) -> 3.2604289 | E92: =IF(E86=0,0,E24/E86*100) -> 2.8961406 | F92: =IF(F86=0,0,F24/F86*100) -> 2.813922
B93: Valeur brute matériel / amortissements | C93: =IF(C26=0,0,C86/C26*100) -> 0 | D93: =IF(D26=0,0,D86/D26*100) -> 1325.0107 | E93: =IF(E26=0,0,E86/E26*100) -> 1319.4619 | F93: =IF(F26=0,0,F86/F26*100) -> 1340.4502
B94: CAF corrigée / CA | C94: =IF(C22=0,0,C44/C22*100) -> -19.433342 | D94: =IF(D22=0,0,D44/D22*100) -> -7.3846557 | E94: =IF(E22=0,0,E44/E22*100) -> -14.308556 | F94: =IF(F22=0,0,F44/F22*100) -> 0.20743854
B95: Créance / CA TTC | C95: =IF(C15=0,0,C79/(C23*1.055+(C15-C23)*1.2)*100) -> 16.404579 | D95: =IF(D15=0,0,D79/(D23*1.1+(D15-D23)*1.2)*100) -> 21.033857 | E95: =IF(E15=0,0,E79/(E23*1.1+(E15-E23)*1.2)*100) -> 24.535233 | F95: =IF(F15=0,0,F79/(F23*1.1+(F15-F23)*1.2)*100) -> 24.769347
A96: critere | C96: TC | D96: TC | E96: TC | F96: TC
A97: Compte=(40-47) | B97: Comptes de tiers | C97: 25693.82 | D97: 86025.49 | E97: 24210.03 | F97: 387762.15
A98: Compte=(51) | B98: Comptes banques | C98: 0 | D98: 0 | E98: 0 | F98: 0
A99: Compte=(40-4190;4192-458;46-476;478-479;51-518) | B99: Dettes (parties en TC) | C99: 25693.82 | D99: 86025.49 | E99: 24210.03 | F99: 387762.15
A100: critere | C100: SO | D100: SO | E100: SO | F100: SO
...

Sheet Publipostage
A1: nom_cuma | B1: num_gestion | C1: debut_periode | D1: fin_periode | E1: commune | F1: num_agrement | G1: comptable_nom | H1: comptable_tel | I1: comptable_mail | J1: nb_adherent | K1: ca | L1: ca_n1 | M1: ca_n2 | N1: ebe | O1: ebe_n1 | P1: ebe_n2 | Q1: rc | R1: rc_n1 | S1: rc_n2 | T1: rex | U1: rex_n1 | V1: rex_n2 | W1: rnc | X1: rnc_n1 | Y1: rnc_n2 | Z1: ca_corrige | AA1: ca_corrige_n1 | AB1: ca_corrige_n2 | AC1: entretien | AD1: entretien_n1 | AE1: entretien_n2 | AF1: entretien_ca | AG1: entretien_ca_n1 | AH1: entretien_ca_n2 | AI1: amort_ca | AJ1: amort_ca_n1 | AK1: amort_ca_n2 | AL1: tx_vetuste | AM1: tx_vetuste_n1 | AN1: tx_vetuste_n2 | AO1: chgsal | AP1: chgsal_n1 | AQ1: chgsal_n2 | AR1: chgsal_ca | AS1: chgsal_ca_n1 | AT1: chgsal_ca_n2 | AU1: carburant | AV1: carburant_n1 | AW1: carburant_n2 | AX1: ffinancier_ca | AY1: ffinancier_ca_n1 | AZ1: ffinancier_ca_n2 | BA1: res_hors_revente | BB1: dot_amort_reprise_prov | BC1: remb_emprunt | BD1: CAF | BE1: CAF_n1 | BF1: CAF_n2 | BG1: achat_immo | BH1: augment_PSCRCA | BI1: emprunt_LMT | BJ1: revente_immo | BK1: variation_KS | BL1: subvention | BM1: besoin_autofin | BN1: besoin_autofin_n1 | BO1: besoin_autofin_n2 | BP1: var_FdR | BQ1: var_FdR_n1 | BR1: var_FdR_n2 | BS1: fd_roulement | BT1: fd_roulement_n1 | BU1: fd_roulement_n2 | BV1: fd_roulement_ca | BW1: fd_roulement_ca_n1 | BX1: fd_roulement_ca_n2 | BY1: actif_circulant | BZ1: actif_circulant_n1 | CA1: actif_circulant_n2 | CB1: besoin_fdr | CC1: besoin_fdr_n1 | CD1: besoin_fdr_n2 | CE1: creance_ca | CF1: creance_ca_n1 | CG1: creance_ca_n2 | CH1: treso_net | CI1: treso_net_n1 | CJ1: treso_net_n2 | CK1: CS_CA | CL1: CS_CA_n1 | CM1: CS_CA_n2 | CN1: CS_val_brute_mat | CO1: CS_val_brute_mat_n1 | CP1: CS_val_brute_mat_n2 | CQ1: CS_k_propres | CR1: CS_k_propres_n1 | CS1: CS_k_propres_n2 | CT1: tx_endette | CU1: tx_endette_n1 | CV1: tx_endette_n2 | CW1: k_propres_passif | CX1: k_propres_passif_n1 | CY1: k_propres_passif_n2 | CZ1: subvention | DA1: variation_cap | DB1: vetuste | DC1: vetuste_n1 | DD1: vetuste_n2 | DE1: Num_gest | DF1: Capitaux_Permanent | DG1: Capitaux_Permanent_n1 | DH1: Capitaux_Permanent_n2 | DI1: Creance_1an | DJ1: Creance_1an_n1 | DK1: Creance_1an_n2 | DL1: Emprunt_recevoir | DM1: Emprunt_recevoir_n1 | DN1: Emprunt_recevoir_n2 | DO1: Emprunt_anticipation | DP1: Emprunt_anticipation_n1 | DQ1: Emprunt_anticipation_n2 | DR1: provision_creance_n | DS1: provision_creance_n1 | DT1: entretien_valBruteMateriel_n | DU1: entretien_valBruteMateriel_n1 | DV1: entretien_valBruteMateriel_n2 | DW1: valBruteMateriel_amort_n | DX1: valBruteMateriel_amort_n1 | DY1: valBruteMateriel_amort_n2 | DZ1: CAF_CA_n | EA1: CAF_CA_n1 | EB1: CAF_CA_n2 | EC1: Creance_CA_TTC_n | ED1: Creance_CA_TTC_n1 | EE1: Creance_CA_TTC_n2 | EF1: Investissement_moy_N_n1_n2 | EG1: Investissement_moy_N_n1_n2_Sur_N3 | EH1: Immo_n | EI1: Immo_n1 | EJ1: Immo_n2 | EK1: ResultatIS_n | EL1: ResultatIS_n1 | EM1: ResultatIS_n2 | EN1: plu_moins_value_n | EO1: plu_moins_value_n1 | EP1: plu_moins_value_n2 | EQ1: res_courant_plu_val_n | ER1: res_courant_plu_val_n1 | ES1: res_courant_plu_val_n2
A2: =GuideGestion!C1 -> CUMA DE TEST | B2: =GuideGestion!C2 -> TEST999001 | C2: =GuideGestion!C12 -> 01/01/2025 | D2: =GuideGestion!C13 -> 31/12/2025 | E2: =GuideGestion!C3 -> PARIS | F2: =GuideGestion!C4 -> AGR999001 | G2: =GuideGestion!C8 -> Ali BABA | H2: =GuideGestion!C9 -> 01.02.03.04.05 | I2: =GuideGestion!C10 -> ali.baba@Cuma.fr | J2: =GuideGestion!C11 -> 64 | K2: =GuideGestion!C15 -> 562308.95 | L2: =GuideGestion!D15 -> 500655.03 | M2: =GuideGestion!E15 -> 517570.12 | N2: =GuideGestion!C16 -> 235445.07 | O2: =GuideGestion!D16 -> 223675.74 | P2: =GuideGestion!E16 -> 261796.64 | Q2: =GuideGestion!C17 -> 234249.79 | R2: =GuideGestion!D17 -> -1379.57 | S2: =GuideGestion!E17 -> 64422.42 | T2: =GuideGestion!C19 -> 118480.12 | U2: =GuideGestion!D19 -> 11409.29 | V2: =GuideGestion!E19 -> 27443.23 | W2: =GuideGestion!C20 -> 352729.91 | X2: =GuideGestion!D20 -> 10029.72 | Y2: =GuideGestion!E20 -> 91865.65 | Z2: =GuideGestion!C22 -> 562308.95 | AA2: =GuideGestion!D22 -> 500655.03 | AB2: =GuideGestion!E22 -> 517570.12 | AC2: =GuideGestion!C24 -> 93716.75 | AD2: =GuideGestion!D24 -> 80962.24 | AE2: =GuideGestion!E24 -> 68307.68 | AF2: =GuideGestion!C25 -> 16.666416 | AG2: =GuideGestion!D25 -> 16.171263 | AH2: =GuideGestion!E25 -> 13.197763 | AI2: =GuideGestion!C27 -> 0 | AJ2: =GuideGestion!D27 -> 37.432585 | AK2: =GuideGestion!E27 -> 34.536938 | AL2: =GuideGestion!C65 -> 30.345722 | AM2: =GuideGestion!D65 -> 37.368341 | AN2: =GuideGestion!E65 -> 32.140424 | AO2: =GuideGestion!C28 -> 67728.85 | AP2: =GuideGestion!D28 -> 32405.75 | AQ2: =GuideGestion!E28 -> 36312.8 | AR2: =GuideGestion!C29 -> 12.044775 | AS2: =GuideGestion!D29 -> 6.4726704 | AT2: =GuideGestion!E29 -> 7.0160155 | AU2: =GuideGestion!C30 -> 65706.47 | AV2: =GuideGestion!D30 -> 60001.4 | AW2: =GuideGestion!E30 -> 78623.72 | AX2: =GuideGestion!C32 -> 4.4684492 | AY2: =GuideGestion!D32 -> 5.1131195 | AZ2: =GuideGestion!E32 -> 3.8009652 | BA2: =GuideGestion!C34 -> 201729.91 | BB2: =GuideGestion!C37 -> 0 | BC2: =GuideGestion!C41 -> 311005.33 | BD2: =GuideGestion!C44 -> -109275.42 | BE2: =GuideGestion!D44 -> -36971.65 | BF2: =GuideGestion!E44 -> -74056.81 | BG2: =GuideGestion!C42 -> 600907.92 | BH2: =GuideGestion!C47 -> 68.85 | BI2: =GuideGestion!C52 -> 566600 | BJ2: =GuideGestion!C48 -> 151000 | BK2: =GuideGestion!C50 -> 0 | BL2: =GuideGestion!C53 -> 0 | BM2: =GuideGestion!C55 -> -116623.23 | BN2: =GuideGestion!D55 -> 336.79 | BO2: =GuideGestion!E55 -> -555878.85 | BP2: =GuideGestion!C60 -> 7347.81 | BQ2: =GuideGestion!D60 -> -37387.99 | BR2: =GuideGestion!E60 -> 493383.67 | BS2: =GuideGestion!C74 -> 295385.8 | BT2: =GuideGestion!D74 -> 288037.99 | BU2: =GuideGestion!E74 -> 325425.98 | BV2: =GuideGestion!C75 -> 52.530873 | BW2: =GuideGestion!D75 -> 57.532227 | BX2: =GuideGestion!E75 -> 62.875728 | BY2: =GuideGestion!C76+GuideGestion!C78 -> 403551.6 | BZ2: =GuideGestion!D76+GuideGestion!D78 -> 329063.79 | CA2: =GuideGestion!E76+GuideGestion!E78 -> 396993.68 | CB2: =BY2-GuideGestion!C99-GuideGestion!C101+GuideGestion!C106 -> 367818.69 | CC2: =BZ2-GuideGestion!D99-GuideGestion!D101+GuideGestion!D106 -> 232999.21 | CD2: =CA2-GuideGestion!E99-GuideGestion!E101+GuideGestion!E106 -> 363523.11 | CE2: =GuideGestion!C80 -> 18.452699 | CF2: =GuideGestion!D80 -> 24.116849 | CG2: =GuideGestion!E80 -> 28.158283 | CH2: =BS2-CB2 -> -72432.89 | CI2: =BT2-CC2 -> 55038.78 | CJ2: =BU2-CD2 -> -38097.13 | CK2: =GuideGestion!C85 -> 26.829023 | CL2: =GuideGestion!D85 -> 30.132924 | CM2: =GuideGestion!E85 -> 27.159991 | CN2: =GuideGestion!C88 -> 4.9336205 | CO2: =GuideGestion!D88 -> 6.0753609 | CP2: =GuideGestion!E88 -> 5.9600367 | CQ2: =GuideGestion!C91 -> 13.943639 | CR2: =GuideGestion!D91 -> 20.688374 | CS2: =GuideGestion!E91 -> 20.046114 | CT2: =GuideGestion!C107 -> 53.428895 | CU2: =GuideGestion!D107 -> 57.124159 | CV2: =GuideGestion!E107 -> 61.14275 | CW2: =GuideGestion!C105 -> 41.735645 | CX2: =GuideGestion!D105 -> 36.880368 | CY2: =GuideGestion!E105 -> 34.553129 | CZ2: =GuideGestion!C53 -> 0 | DA2: =GuideGestion!C50 -> 0 | DB2: =GuideGestion!C65 -> 30.345722 | DC2: =GuideGestion!D65 -> 37.368341 | DD2: =GuideGestion!E65 -> 32.140424 | DE2: =GuideGestion!C2 -> TEST999001 | DF2: =IF((GuideGestion!C90+GuideGestion!C106+GuideGestion!C72)<>0,GuideGestion!C90/(GuideGestion!C90+GuideGestion!C106+GuideGestion!C72),0) -> 0.42318965 | DG2: =IF((GuideGestion!D90+GuideGestion!D106+GuideGestion!D72)<>0,GuideGestion!D90/(GuideGestion!D90+GuideGestion!D106+GuideGestion!D72),0) -> 0.38763715 | DH2: =IF((GuideGestion!E106+GuideGestion!E90+GuideGestion!E72)<>0,GuideGestion!E90/(GuideGestion!E106+GuideGestion!E90+GuideGestion!E72),0) -> 0.35132546 | DI2: =GuideGestion!C45 -> 0 | DJ2: =GuideGestion!D45 -> 25500.34 | DK2: =GuideGestion!E45 -> 10108.65 | DL2: =GuideGestion!C54 -> 0 | DM2: =GuideGestion!D54 -> 0 | DN2: =GuideGestion!E54 -> 0 | DO2: =GuideGestion!C39 -> 0 | DP2: =GuideGestion!D39 -> 0 | DQ2: =GuideGestion!E39 -> 0 | DR2: =GuideGestion!C59 -> 0 | DS2: =GuideGestion!D59 -> -79.55 | DT2: =GuideGestion!C92 -> 3.0648068 | DU2: =GuideGestion!D92 -> 3.2604289 | DV2: =GuideGestion!E92 -> 2.8961406 | DW2: =GuideGestion!C93 -> 0 | DX2: =GuideGestion!D93 -> 1325.0107 | DY2: =GuideGestion!E93 -> 1319.4619 | DZ2: =GuideGestion!C94 -> -19.433342 | EA2: =GuideGestion!D94 -> -7.3846557 | EB2: =GuideGestion!E94 -> -14.308556 | EC2: =GuideGestion!C95 -> 16.404579 | ED2: =GuideGestion!D95 -> 21.033857 | EE2: =GuideGestion!E95 -> 24.535233 | EF2: =IF(SUM(GuideGestion!C43:E43)>0,AVERAGE(GuideGestion!C43:E43),0) -> 368385.97 | EG2: =IF(GuideGestion!F87<>0,Publipostage!EF2/GuideGestion!F87,0)*100 -> 15.870409 | EH2: =GuideGestion!C43 -> 574657.92 | EI2: =GuideGestion!D43 -> 143350 | EJ2: =GuideGestion!E43 -> 387150 | EK2: =GuideGestion!C18 -> 0 | EL2: =GuideGestion!D18 -> 0 | EM2: =GuideGestion!E18 -> 0 | EN2: =GuideGestion!C49 -> 32500 | EO2: =GuideGestion!D49 -> 0 | EP2: =GuideGestion!E49 -> 0 | EQ2: =Q2-EN2 -> 201749.79 | ER2: =R2-EO2 -> -1379.57 | ES2: =S2-EP2 -> 64422.42
