Workbook
Name a: Resultat!$1:$7
Name agios_four_N: Resultat!$H$95
Name Assurances: Resultat!$H$51
Name aut_achat_N: Resultat!$H$46
Name aut_ch_except_N: Resultat!$H$118
Name aut_ch_expl_N: Resultat!$H$71
Name aut_ch_externe_N: Resultat!$H$57
Name aut_ch_fi_N: Resultat!$H$97
Name aut_prod_except_N: Resultat!$H$112
Name aut_prod_fi_N: Resultat!$H$86
Name aut_tx_N: Resultat!$H$18
Name Bilan: [1]actif!$F$46
Name CA_N: Resultat!$H$24
Name carburant_N: Resultat!$H$41
Name ChargSoc_N: Resultat!$F$62
Name credit_debit: [2]compta_n!$E$1:$E$65536
Name debit_credit: [2]compta_n!$D$1:$D$65536
Name doc: Resultat!$H$52
Name dot_amort_except_N: Resultat!$H$117
Name dot_amort_fi_N: Resultat!$H$98
Name e: Resultat!$1:$7
Name ent_rep_N: Resultat!$H$50
Name Excel_BuiltIn_Print_Area_5: Resultat!$A$1:$K$129
Name Excel_BuiltIn_Print_Titles_5: Resultat!$1:$7
Name honoraires_N: Resultat!$H$54
Name indemn_adm_N: Resultat!$H$70
Name interet_banque_N: Resultat!$H$96
Name location_N: Resultat!$H$49
Name lub_piece_N: Resultat!$H$39
Name M_actif_circ: Actif!$H$49
Name M_Actif_immo: Actif!$H$33
Name M_aut_immo: Actif!$H$31
Name M_aut_immo_corp: Actif!$H$23
Name M_aut_immo_incorp: Actif!$H$15
Name M_avance: Actif!$H$42
Name M_charge_differe: Actif!#REF!
Name M_construc: Actif!$H$21
Name M_creance_adh: Actif!$H$43
Name M_creance_adh_cs: Actif!$H$44
Name M_frais_etab: Actif!$H$14
Name M_immo_en_cour: Actif!$H$24
Name M_inst_tech: Actif!$H$22
Name M_marchand: Actif!$H$38
Name M_mat_conso: Actif!$H$36
Name M_participation: Actif!$H$27
Name M_pers: Actif!$H$45
Name M_terrain: Actif!$H$20
Name mat_incorpo_N: Resultat!$H$42
Name N_actif_circ_amo: Actif!$E$49
Name N_actif_circ_brut: Actif!$D$49
Name N_Actif_immo_amo: Actif!$E$33
Name N_Actif_immo_brut: Actif!$D$33
Name N_Actif_tot_amo: Actif!$E$52
Name N_Actif_tot_brut: Actif!$D$52
Name N_aut_immo_amo: Actif!$E$31
Name N_aut_immo_brut: Actif!$D$31
Name N_aut_immo_corp_amo: Actif!$E$23
Name N_aut_immo_corp_brut: Actif!$D$23
Name N_aut_immo_corp_net: Actif!$F$23
Name N_aut_immo_incorp: Actif!$D$15

Sheet Temp
B1: Nom de la Cuma | C1: TEST
B2: Numéro d'agrément | C2: 999D0001
B3: Numéro de gestion | C3: 999001
B4: Code postal | C4: 75011
B5: Ville | C5: PARIS
B6: Adresse | C6: Rue Sedaine
B7: Siren | C7: 99988877700021
B8: Cloture N
B9: Cloture N-1 | C9: clot
B10: Cloture N-2 | C10: clot
B11: ETB
A12: datedebut | C12: 01/01/2025 | D12: 01/01/2024 | E12: 01/01/2023
A13: datefin | C13: 31/12/2025 | D13: 31/12/2024 | E13: 31/12/2023
A14: critere | C14: SO | D14: SO
A15: Compte=(704-706;7094-7096) credit=positif | B15: Activité de services | C15: 553345.57 | D15: 473301.03 | E15: 497531.42
A16: compte=(70612;709612) | B16: Dont Travaux de culture | C16: 122703.56 | D16: 100350.24 | E16: 124658.76
A17: compte=(70613;709613) | B17: Dont Travaux de récolte | C17: 244876.81 | D17: 227035.41 | E17: 227631.48
A18: compte=(7063;70963) | B18: Dont Travaux inter CUMA | C18: 0 | D18: 0 | E18: 0
A19: compte=(7062;70962) | B19: Dont Travaux tiers non associés | C19: 0 | D19: 0 | E19: 0
A20: Compte=(70614-70618;7094;70611) | B20: Dont Autres travaux | C20: 185765.2 | D20: 145915.38 | E20: 145241.18
A21: Compte=(703;708;7090;7093;7098) | B21: Produits des activités annexes | C21: 8963.38 | D21: 27354 | E21: 20038.7
A22: compte=(7084) | B22: Mise à disposition du personnel | C22: 0 | D22: 5351 | E22: 1674
A23: Compte=(713) | B23: Activité de services | C23: 0 | D23: 0 | E23: 0
A24: compte=(72) | B24: Production immobilisée | C24: 0 | D24: 0 | E24: 0
A25: compte=(74) | B25: Subventions d'exploitation | C25: 8433.84 | D25: 790.39 | E25: 0
A26: compte=(747) | B26: Dont Quote-part des subventions d'investissement virées au résultat de l'exercice | C26: 0 | D26: 790.39 | E26: 0
... A92: Compte=(70;74-746;748-749;60;61;62;63;64) credit = positif | B92: Excédent brut d'exploitation | C92: 235445.07 | D92: 223675.74 | E92: 261796.64
A93: datedebut | C93: 01/01/2000 | D93: 01/01/2000 | E93: 01/01/2000
A94: compte=(109) credit=negatif | B94: Capital souscrit non appelé | C94: 0 | D94: 0 | E94: 0
A95: compte=(201) credit=negatif | B95: Frais d'établissement (brut) | C95: 0 | D95: 0 | E95: 0
A96: compte=(2801;2901) credit=positif | B96: Frais d'établissement (amort) | C96: 0 | D96: 0 | E96: 0
A97: compte=(203) credit=negatif | B97: Frais de recherche et de développement (brut) | C97: 0 | D97: 0 | E97: 0
A98: compte=(2803;2903) credit=positif | B98: Frais de recherche et de développement (amort) | C98: 0 | D98: 0 | E98: 0
A99: compte=(205) credit=negatif | B99: Concessions,brevets,licences, marques, procédés, logiciels, droits et valeurs similaires(brut) | C99: 0 | D99: 0 | E99: 0
A100: compte=(2805;2905) credit=positif | B100: Concessions,brevets,licences, marques, procédés, logiciels, droits et valeurs similaires (amort) | C100: 0 | D100: 0 | E100: 0
A101: compte=(200;202;204;206-209) credit=negatif | B101: Autres immobilisations incorporelles (brut) | C101: 0 | D101: 0 | E101: 0
A102: compte=(2800;2802;2804;2806-2809;2900;2902;2904;2906-2909) credit=positif | B102: Autres immobilisations incorporelles (amort) | C102: 0 | D102: 0 | E102: 0
A103: compte=(237) credit=negatif | B103: Avances et acomptes sur immobilisations incorporelles (brut) | C103: 0 | D103: 0 | E103: 0
A104: compte=(2937) credit=positif | B104: Avances et acomptes sur immobilisations incorporelles (amort) | C104: 0 | D104: 0 | E104: 0
A105: compte=(211;212) credit=negatif | B105: Terrains (brut) | C105: 5180 | D105: 5180 | E105: 5180
... A134: compte=(4091) credit=negatif | B134: Avances et acomptes versés sur commandes et apports | C134: 0 | D134: 0 | E134: 0
A135: critere | C135: TD | D135: TD
A136: compte=(450;452-454;457-459) credit=negatif | B136: Créances Associés coopérateurs et comptes rattachés (brut) | C136: 103761.18 | D136: 120742.22 | E136: 145738.86
A137: critere | C137: TC | D137: TC
A138: compte=(4950;4952-4954;4957-4959) credit=positif | B138: Créances Associés coopérateurs et comptes rattachés (amort) | C138: 8506.71 | D138: 8506.71 | E138: 8427.16
A139: critere | C139: TD | D139: TD
A140: compte=(41-4190;4192-419) credit=negatif | B140: Clients et comptes rattachés (brut) | C140: 4981.17 | D140: 5014.38 | E140: 31438.78
A141: critere | C141: TC | D141: TC
A142: compte=(491) credit=positif | B142: Clients et comptes rattachés (amort) | C142: 0 | D142: 0 | E142: 0
A143: critere | C143: TD | D143: TD
A144: Compte=(40-4090;4092-4099;42-44;46-4759;477-479;455;451) credit=negatif | B144: Autres créances (brut) | C144: 68114.86 | D144: 10756.21 | E144: 3596.24
A145: critere | C145: TC | D145: TC
A146: compte=(4951;4955;496) credit=positif | B146: Autres créances (amort) | C146: 0 | D146: 0 | E146: 0
A147: critere | C147: TD | D147: TD
A148: compte=(456) credit=negatif | B148: Capital à verser (brut) | C148: 1688 | D148: 11918 | E148: 10464
A149: compte=(4956) credit=positif | B149: Capital à verser (amort) | C149: 0 | D149: 0 | E149: 0
A150: critere | C150: SO | D150: SO
A151: compte=(50) credit=negatif | B151: Valeurs mobilières de placement (brut) | C151: 0 | D151: 0 | E151: 0
A152: compte=(590) credit=positif | B152: Valeurs mobilières de placement (amort) | C152: 0 | D152: 0 | E152: 0
A153: compte=(53;54) credit=negatif | B153: Disponibilités (sans 51)(brut) | C153: 0 | D153: 0 | E153: 0
A154: critere | C154: TD | D154: TD
A155: compte=(51-518) credit=negatif | B155: Disponibilités (le 51)(brut) | C155: 248425.87 | D155: 264384.13 | E155: 200573.4
A156: critere | C156: SO | D156: SO
A157: Compte=(486) credit=negatif | B157: Charges constatées d'avance (brut) | C157: 0 | D157: 0 | E157: 0
A158: compte=(4986) credit=positif | B158: Charges constatées d'avance (amort) | C158: 0 | D158: 0 | E158: 0
A159: compte=(481) credit=negatif | B159: Charges à répartir sur plusieurs exercices (brut) | C159: 0 | D159: 0 | E159: 0
A160: compte=(169) credit=negatif | B160: Primes de remboursement des emprunts (brut) | C160: 0 | D160: 0 | E160: 0
A161: compte=(476) credit=negatif | B161: Ecarts de conversion Actif | C161: 0 | D161: 0 | E161: 0
A162: compte=(101) credit=positif | B162: Capital (Y compris capital souscrit fraction non exigée) | C162: 150862 | D162: 150862 | E162: 140572
A163: compte=(1013) | B163: dont versé | C163: 150572 | D163: 138944 | E163: 129304
A164: compte=(104) | B164: Droits d'entrée | C164: 0 | D164: 0 | E164: 0
A165: compte=(105) | B165: Ecarts de réévaluation | C165: 0 | D165: 0 | E165: 0
A166: compte=(1061) | B166: Réserve légale | C166: 59116.92 | D166: 59116.92 | E166: 51291.48
A167: compte=(10621) | B167: - provenant des subventions reçues de l'Etat, des collectivités publiques et des établissements publics | C167: 65079.25 | D167: 65079.25 | E167: 60859.75
A168: compte=(10622) | B168: - provenant des opérations TNA | C168: 0 | D168: 0 | E168: 0
... A188: compte=(164;16884;519) | B188: Emprunts et dettes auprès des établissements de crédits (sans 51, avec 519) | C188: 1484732.6 | D188: 1161997.9 | E188: 1304010.4
A189: critere | C189: TC | D189: TC
A190: compte=(51-518) | B190: Emprunts et dettes auprès des établissements de crédits (le 51) | C190: 0 | D190: 0 | E190: -200573.4
A191: critere | C191: SO | D191: SO
A192: compte=(519) | B192: Dont concours bancaires courants et soldes créditeurs de banques (le 519) | C192: 0 | D192: 0 | E192: 0
A193: critere | C193: TC | D193: TC
A194: compte=(512;514;517;5181) | B194: Dont concours bancaires courants et soldes créditeurs de banques | C194: 0 | D194: 0 | E194: -200227.71
A195: critere | C195: SO | D195: SO
A196: Compte=(16411;16421;16431;16441;16451;16461;16471;16481;16491) | B196: Dont emprunts à court terme | C196: 89620 | D196: 22480 | E196: 53880
A197: Compte=(16412;16422;16432;16442;16452;16462;16472;16482;16492) | B197: Dont emprunts MTS | C197: 0 | D197: 0 | E197: 0
A198: Compte=(16413;16423;16433;16443;16453;16463;16473;16483;16493) | B198: Dont emprunts MT | C198: 1385073.5 | D198: 1129478.8 | E198: 1240869.8
A199: Compte=(16884;16480) | B199: Dont intérêts courus | C199: 10039.09 | D199: 10039.09 | E199: 9260.54
A200: Critere | C200: TC | D200: TC
A201: Compte=(518) | B201: Dont intérêts courus (le518) | C201: 0 | D201: 0 | E201: -345.69
A202: Critere | C202: SO | D202: SO
A203: compte=(16-161;163;165-1670;1672-1673;1675-16881;16883;16885-168;17;188) | B203: Emprunts et dettes financières divers | C203: 0 | D203: 0 | E203: 0
A204: compte=(1675) | B204: Dont emprunts participatifs | C204: 0 | D204: 0 | E204: 0
A205: compte=(4191) | B205: Avances et acomptes reçus sur commandes et cessions | C205: 0 | D205: 0 | E205: 0
A206: critere | C206: TC | D206: TC
A207: Compte=(452-454;4567) | B207: Dettes Associés Coopérateurs et comptes rattachés | C207: 262 | D207: 262 | E207: -144934.86
A208: compte=(40-403;406-4083;4085-409) | B208: Dettes Fournisseurs et comptes rattachés | C208: 0 | D208: 32163.03 | E208: -781.34
A209: compte=(42-44) | B209: Dettes fiscales et sociales | C209: 16778.32 | D209: 17716.36 | E209: -4854.78
A210: critere | C210: SO | D210: SO
A211: compte=(269;279) | B211: Dettes sur immobilisations et comptes rattachés (comptes 2) | C211: 0 | D211: 0 | E211: 0
A212: critere | C212: TC | D212: TC
...

Sheet Actif
B2: =Temp!C1 -> TEST | F2: ="Exercice "&RIGHT(Temp!C13,4) -> Exercice 2025
C3: ="Dossier "&Temp!C3 -> Dossier 999001 | F3: du | H3: =Temp!C12 -> 01/01/2025
C4: ="Numéro d'agrément : "&Temp!C2 -> Numéro d'agrément : 999D0001 | F4: au | H4: =Temp!C13 -> 31/12/2025
B5: BILAN
B6: ACTIF
A10: ACTIF | D10: BRUT | E10: AMORT | F10: NET N | H10: NET N-1
A11: 109 | C11: Capital souscrit non appelé | D11: =Temp!C94 -> 0 | F11: =D11 -> 0 | H11: =Temp!D94 -> 0
A12: ACTIF IMMOBILISE
B13: IMMOBILISAT. INCORPO.
A14: 201 | C14: Frais d'établissement | D14: =Temp!C95 -> 0 | E14: =Temp!C96 -> 0 | F14: =N_Frais_etab_brut-N_Frais_etab_amo -> 0 | H14: =Temp!D95-Temp!D96 -> 0
A15: 203 | C15: Frais de recherche et développement | D15: =Temp!C97 -> 0 | E15: =Temp!C98 -> 0 | F15: =N_aut_immo_incorp-N_aut_immo_incorp_amo -> 0 | H15: =Temp!D97-Temp!D98 -> 0
A16: 205 | C16: Concessions, brevets, licences, marques, procédés, logiciels, droits et valeurs similaires | D16: =Temp!C99 -> 0 | E16: =Temp!C100 -> 0 | F16: =D16-E16 -> 0 | H16: =Temp!D99-Temp!D100 -> 0
A17: 20 | C17: Autres immobilisations incorporelles | D17: =Temp!C101 -> 0 | E17: =Temp!C102 -> 0 | F17: =D17-E17 -> 0 | H17: =Temp!D101-Temp!D102 -> 0
A18: 237 | C18: Avances et acomptes sur immobilisations incorporelles | D18: =Temp!C103 -> 0 | E18: =Temp!C104 -> 0 | F18: =D18-E18 -> 0 | H18: =Temp!D103-Temp!D104 -> 0
B19: IMMOBILISAT. CORPO.
A20: 211+212 | C20: Terrains | D20: =Temp!C105 -> 5180 | E20: =Temp!C106 -> 0 | F20: =N_terrain_brut-N_terrain_amo -> 5180 | H20: =Temp!D105-Temp!D106 -> 5180
A21: 213+214 | C21: Constructions | D21: =Temp!C107 -> 41759.49 | E21: =Temp!C108 -> 34670.69 | F21: =N_construc_brut-N_construc_amo -> 7088.8 | H21: =Temp!D107-Temp!D108 -> 7088.8
A22: 215 | C22: Install. techniques, matériels et outillage | D22: =Temp!C109 -> 3057835.5 | E22: =Temp!C110 -> 927922.27 | F22: =N_inst_tech_brut-N_inst_tech_amo -> 2129913.2 | H22: =Temp!D109-Temp!D110 -> 1555255.3
A23: 21+22 | C23: Autres immobilisations corporelles | D23: =Temp!C111 -> 0 | E23: =Temp!C112 -> 0 | F23: =N_aut_immo_corp_brut-N_aut_immo_corp_amo -> 0 | H23: =Temp!D111-Temp!D112 -> 0
A24: 23 | C24: Immobilisations corporelles en cours | D24: =Temp!C113 -> 0 | F24: =N_immo_en_cour_brut-N_immo_en_cour_amo -> 0 | H24: =Temp!D113 -> 0
A25: 238 | C25: Avances et acomptes sur immobilisations corporelles | D25: =Temp!C114 -> 26250 | E25: =Temp!C115 -> 0 | F25: =D25-E25 -> 26250 | H25: =Temp!D114-Temp!D115 -> 0
B26: IMMOBILISAT. FINANCIERES
A27: 262 | C27: Participations à des org. Coop. agricoles | D27: =Temp!C116 -> 947.92 | E27: =Temp!C117 -> 0 | F27: =N_participation_brut-N_participation_amo -> 947.92 | H27: =Temp!D116-Temp!D117 -> 947.92
A28: 26 | C28: Autres participations | D28: =Temp!C118 -> 0 | E28: =Temp!C119 -> 0 | F28: =D28-E28 -> 0 | H28: =Temp!D118-Temp!D119 -> 0
A29: 267+268 | C29: Créances rattachées à des participations | D29: =Temp!C120 -> 0 | E29: =Temp!C121 -> 0 | F29: =D29-E29 -> 0 | H29: =Temp!D120-Temp!D121 -> 0
A30: 271+272 | C30: Autres titres immobilisés, PS banques... | D30: =Temp!C122 -> 2249.1 | E30: =Temp!C123 -> 0 | F30: =D30-E30 -> 2249.1 | H30: =Temp!D122-Temp!D123 -> 2180.25
A31: 274 | C31: Prêts | D31: =Temp!C124 -> 0 | E31: =Temp!C125 -> 0 | F31: =N_aut_immo_brut-N_aut_immo_amo -> 0 | H31: =Temp!D124-Temp!D125 -> 0
A32: 27 | C32: Autres immobilisations financières | D32: =Temp!C126 -> 0 | E32: =Temp!C127 -> 0 | F32: =N_reste_immo_brut-N_reste_immo_amo -> 0 | H32: =Temp!D126-Temp!D127 -> 0
C33: TOTAL ACTIF IMMOBILISE | D33: =SUM(D27:D32,D20:D25,D14:D18) -> 3134222 | E33: =SUM(E27:E32,E20:E25,E14:E18) -> 962592.96 | F33: =N_Actif_immo_brut-N_Actif_immo_amo -> 2171629.1 | H33: =SUM(H27:H32,H20:H25,H14:H18) -> 1570652.3
A34: ACTIF CIRCULANT
B35: STOCKS ET EN-COURS
A36: 32 | C36: Matières consommables et emballage | D36: =Temp!C128 -> 2274.34 | E36: =Temp!C129 -> 0 | F36: =N_mat_conso_brut-N_mat_conso_amo -> 2274.34 | H36: =Temp!D128-Temp!D129 -> 2274.34
A37: 34 | C37: En cours de production de services | D37: =Temp!C130 -> 0 | E37: =Temp!C131 -> 0 | F37: =N_encours_Prod_brut-N_aut_stock_amo -> 0 | H37: =Temp!D130-Temp!D131 -> 0
C38: Marchandises
A39: 375 | C39: Activité d'approvisionnement | D39: =Temp!C132 -> 0 | E39: =Temp!C133 -> 0 | F39: =D39-E39 -> 0 | H39: =Temp!D132-Temp!D133 -> 0
A40: 4091 | C40: Avances et acomptes versés sur commandes et apports | D40: =Temp!C134 -> 0 | F40: =D40 -> 0 | H40: =Temp!D134 -> 0
B41: CREANCES
A42: 45 | C42: Créances associés coopérateurs et comptes rattachés (1) | D42: =Temp!C136 -> 103761.18 | E42: =Temp!C138 -> 8506.71 | F42: =Temp!C136-Temp!C138 -> 95254.47 | H42: =Temp!D136-Temp!D138 -> 112235.51
A43: 41 | C43: Clients et comptes rattachés | D43: =Temp!C140 -> 4981.17 | E43: =Temp!C142 -> 0 | F43: =Temp!C140-Temp!C142 -> 4981.17 | H43: =Temp!D140-Temp!D142 -> 5014.38
A44: 40-49 | C44: Autres créances | D44: =Temp!C144 -> 68114.86 | E44: =Temp!C146 -> 0 | F44: =Temp!C144-Temp!C146 -> 68114.86 | H44: =Temp!D144-Temp!D146 -> 10756.21
A45: 456 | C45: Capital à verser | D45: =Temp!C148 -> 1688 | E45: =Temp!C149 -> 0 | F45: =Temp!C148-Temp!C149 -> 1688 | H45: =Temp!D148-Temp!D149 -> 11918
A46: 50 | C46: Valeurs mobilières de placement | D46: =Temp!C151 -> 0 | E46: =Temp!C152 -> 0 | F46: =Temp!C151-Temp!C152 -> 0 | H46: =Temp!D151-Temp!D152 -> 0
A47: 51+53+54 | C47: Disponibilités | D47: =Temp!C153+Temp!C155 -> 248425.87 | F47: =D47 -> 248425.87 | H47: =Temp!D153+Temp!D155 -> 264384.13
A48: 486 | C48: Charges constatées d'avance | D48: =Temp!C157 -> 0 | E48: =Temp!C158 -> 0 | F48: =Temp!C157-Temp!C158 -> 0 | H48: =Temp!D157-Temp!D158 -> 0
C49: TOTAL ACTIF CIRCULANT | D49: =SUM(D36:D48) -> 429245.42 | E49: =SUM(E36:E48) -> 8506.71 | F49: =N_actif_circ_brut-N_actif_circ_amo -> 420738.71 | H49: =SUM(H36:H48) -> 406582.57
A50: 169 | C50: Primes de remb. Emprunt | D50: =Temp!C160 -> 0 | F50: =D50 -> 0 | H50: =Temp!D160 -> 0
A51: 476 | C51: Ecarts de conv. Actif | D51: =Temp!C161 -> 0 | F51: =D51 -> 0 | H51: =Temp!D161 -> 0
A52: TOTAL ACTIF | D52: =N_Actif_immo_brut+N_actif_circ_brut+D50+D51+D11 -> 3563467.4 | E52: =N_Actif_immo_amo+N_actif_circ_amo -> 971099.67 | F52: =N_Actif_tot_brut-N_Actif_tot_amo -> 2592367.8 | H52: =M_actif_circ+M_Actif_immo+H50+H51+H11 -> 1977234.9
C53: (1) dont créances à plus de 1 an | F53: =Temp!C91 -> 0 | H53: =Temp!D91 -> 25500.34
F64: =Passif!D73 -> 0
F65: =Passif!D72 -> 0
F68: =Passif!D71 -> 0
F69: =Passif!D69 -> 0
F70: =Passif!D68 -> 0
F71: =Passif!F41 -> 0
E73: =Passif!D73+Passif!D72 -> 0

Sheet Passif
B2: =Temp!C1 -> TEST | F2: ="Exercice "&RIGHT(Temp!C13,4) -> Exercice 2025
C3: ="Dossier "&Temp!C3 -> Dossier 999001 | F3: du | H3: =Temp!C12 -> 01/01/2025
C4: ="Numéro d'agrément : "&Temp!C2 -> Numéro d'agrément : 999D0001 | F4: au | H4: =Temp!C13 -> 31/12/2025
B5: BILAN
B6: PASSIF
A10: PASSIF | F10: NET N | H10: NET N-1
A11: CAPITAUX PROPRES
A12: 101 | C12: Capital social | D12: dont versé : | E12: =Temp!C163 -> 150572 | F12: =Temp!C162 -> 150862 | H12: =Temp!D162 -> 150862
A13: 104 | C13: Droits d'entrée | F13: =Temp!C164 -> 0 | H13: =Temp!D164 -> 0
A14: 105 | C14: Écarts de réévaluation | F14: =Temp!C165 -> 0 | H14: =Temp!D165 -> 0
C15: Réserves
A16: 1061 | C16: Réserves légale | F16: =Temp!C166 -> 59116.92 | H16: =Temp!D166 -> 59116.92
C17: Réserves indisponibles
A18: 10621 | C18: - provenant des subventions reçues de l'état, des collectivité publiques et des établissements publics | F18: =Temp!C167 -> 65079.25 | H18: =Temp!D167 -> 65079.25
A19: 10622 | C19: - provenant des opérations TNA | F19: =Temp!C168 -> 0 | H19: =Temp!D168 -> 0
A20: 10623 | C20: - provenant des dévolutions | F20: =Temp!C169 -> 22991.67 | H20: =Temp!D169 -> 22991.67
A21: 10624 à 10649 | C21: - autres | F21: =Temp!C170 -> 0 | H21: =Temp!D170 -> 0
A22: 1063 | C22: Réserves statutaires ou contractuelles | F22: =Temp!C171 -> 0 | H22: =Temp!D171 -> 0
A23: 1064 | C23: Réserves réglementées | F23: =Temp!C172 -> 0 | H23: =Temp!D172 -> 0
A24: 1068 | C24: Autres réserves | F24: =Temp!C173 -> 417702.82 | H24: =Temp!D173 -> 417702.82
A25: 1106 | C25: Report pour parfaire l'intérêt servi aux parts sociales | F25: =Temp!C174 -> 0 | H25: =Temp!D174 -> 0
A26: 1107 | C26: Report à nouveau pour ristournes éventuelles | F26: =Temp!C175 -> 0 | H26: =Temp!D175 -> 0
A27: 11 sauf 1106 & 1107 | C27: Report à nouveau débiteur | F27: =Temp!C177 -> 0 | H27: =Temp!D177 -> 0
A28: 1-5 | C28: Résultat de l'exercice (excédent ou déficit) | F28: =Temp!C178 -> 362759.63 | H28: =Temp!D178 -> 10029.72
A29: 13 | C29: Subventions d'investissement | F29: =Temp!C179 -> 3429.11 | H29: =Temp!D179 -> 3429.11
A30: 131 | C30: Part de la subvention d'investissement affectable au compte de resultat | E30: =Temp!C180 -> 4219.5
A31: 139 | C31: Montant de la subvention d'investissement inscrite au compte de resultat | E31: =Temp!C181 -> -790.39
A32: 14 | C32: Provisions réglementées | F32: =Temp!C182 -> 0 | H32: =Temp!D182 -> 0
A33: TOTAL DES CAPITAUX PROPRES | F33: =SUM(F12:F32) -> 1081941.4 | H33: =SUM(H12:H32) -> 729211.49
A34: AUTRES FONDS PROPRES
A35: 1671 | C35: Produits des émissions de titres participatifs | F35: =Temp!C183 -> 0 | H35: =Temp!D183 -> 0
A36: 1674 | C36: Avances conditionnées | F36: =Temp!C184 -> 0 | H36: =Temp!D184 -> 0
A37: TOTAL DES AUTRES FONDS PROPRES | F37: =SUM(F35:F36) -> 0 | H37: =SUM(H35:H36) -> 0
A38: PROVISIONS POUR RISQUES ET CHARGES
A39: 151 | C39: Provisions pour risques | F39: =Temp!C185 -> 0 | H39: =Temp!D185 -> 0
A40: 15 | C40: Provisions pour charges | F40: =Temp!C186 -> 0 | H40: =Temp!D186 -> 0
A41: TOTAL DES PROVISIONS | F41: =SUM(F39:F40) -> 0 | H41: =SUM(H39:H40) -> 0
A42: DETTES
A43: 162 | C43: Emprunts et dettes coopératifs | F43: =Temp!C187 -> 0 | H43: =Temp!D187 -> 0
A44: 164+51 | C44: Emprunts et dettes auprès des établissements de crédit | F44: =Temp!C188+Temp!C190 -> 1484732.6 | H44: =Temp!D188+Temp!D190 -> 1161997.9
A45: 164*1 | C45: Emprunts à court terme | E45: =Temp!C196 -> 89620 | H45: =Temp!D196 -> 22480
A46: 164*2 | C46: Emprunts MTS | E46: =Temp!C197 -> 0 | H46: =Temp!D197 -> 0
A47: 164*3 | C47: Emprunts à moyen terme | E47: =Temp!C198 -> 1385073.5 | H47: =Temp!D198 -> 1129478.8
A48: 16884 | C48: Intérêts courus | E48: =Temp!C199+Temp!C201 -> 10039.09 | H48: =Temp!D199+Temp!D201 -> 10039.09
A49: 51 | C49: Concours bancaires courants et soldes créditeurs de banques | E49: =Temp!C192+Temp!C194 -> 0 | H49: =Temp!D192+Temp!D194 -> 0
C50: Autres | E50: =F44-E45-E46-E48-E49-E47 -> 0 | H50: =H44-SUM(H45:H49) -> 0
A51: 16+17+188 | C51: Emprunts et dettes financières divers | F51: =Temp!C203 -> 0 | H51: =Temp!D203 -> 0
A52: 1675 | C52: Emprunts participatifs | E52: =Temp!C204 -> 0 | H52: =Temp!D204 -> 0
C53: Autres | E53: =E51-E52 -> 0 | H53: =H51-H52 -> 0
A54: 4191 | C54: Avances et acomptes reçus sur commandes et cessions | F54: =Temp!C205 -> 0 | H54: =Temp!D205 -> 0
A55: 452-454 | C55: Dettes associés coopérateurs et comptes rattachés | F55: =Temp!C207 -> 262 | H55: =Temp!D207 -> 262
A56: 40 | C56: Dettes fournisseurs et comptes rattachés | F56: =Temp!C208 -> 0 | H56: =Temp!D208 -> 32163.03
A57: 42-44 | C57: Dettes fiscales et sociales | F57: =Temp!C209 -> 16778.32 | H57: =Temp!D209 -> 17716.36
A58: 269+279+404+408 | C58: Dettes sur immobilisations et comptes rattachés | F58: =Temp!C211+Temp!C213 -> 0 | H58: =Temp!D211+Temp!D213 -> 29880
A59: 41+45-47 | C59: Autres dettes | F59: =Temp!C214 -> 8653.5 | H59: =Temp!D214 -> 6004.1
A60: COMPTES DE REGULARISATION
A61: 487 | C61: Produits constatés d'avance | F61: =Temp!C216 -> 0 | H61: =Temp!D216 -> 0
A62: TOTAL DETTES | F62: =SUM(PN_dette_fin,F54:F59,F51,F43:F44) -> 1510426.4 | H62: =SUM(PM_dette_fin,H54:H59,H51,H43:H44) -> 1248023.4
A63: 477 | C63: Écarts de conversion passif | F63: =Temp!C218 -> 0 | H63: =Temp!D218 -> 0
C64: =IF(AND(F64="",H64=""),"Différence actif - passif","") | F64: =Actif!F52-PN_tot_cap_prop-Passif!F37-PN_tot_prov-Passif!F62-Passif!F63 -> -6.9849193e-10 | H64: =Actif!H52-PM_tot_cap_prop-H37-PM_tot_prov-H62-H63 -> 2.3283064e-10
A65: TOTAL PASSIF | F65: =PN_tot_cap_prop+F37+PN_tot_prov+F62+F64 -> 2592367.8 | H65: =PM_tot_cap_prop+H37+PM_tot_prov+H62+H64 -> 1977234.9

Sheet Resultat
B2: =Temp!C1 -> TEST | H2: ="Exercice "&RIGHT(Temp!C13,4) -> Exercice 2025
B3: ="Dossier "&Temp!C3 -> Dossier 999001 | H3: du | J3: =Temp!C12 -> 01/01/2025
B4: ="Numéro d'agrément : "&Temp!C2 -> Numéro d'agrément : 999D0001 | H4: au | J4: =Temp!C13 -> 31/12/2025
A6: COMPTE DE RESULTAT
A9: RESULTAT D'EXPLOITATION (Hors Taxes) | H9: TOTAL N | J9: ANNEE N-1 | K9: Var.n/n-1
A10: PRODUITS D'EXPLOITATION
B12: Production vendue et cédée
A13: 704-706 | C13: Activité de services | H13: =Temp!C15 -> 553345.57 | J13: =Temp!D15 -> 473301.03 | K13: =IF(J13>0,(H13-J13)/J13," ") -> 0.16911972
A14: 70612 | C14: Travaux de culture | G14: =Temp!C16 -> 122703.56 | J14: =Temp!D16 -> 100350.24 | K14: =IF(J14>0,(G14-J14)/J14," ") -> 0.22275303
A15: 70613 | C15: Travaux de récolte | G15: =Temp!C17 -> 244876.81 | J15: =Temp!D17 -> 227035.41 | K15: =IF(G15>0,(G15-J15)/J15," ") -> 0.078584217
A16: 7063 | C16: Travaux inter CUMA | G16: =Temp!C18 -> 0 | J16: =Temp!D18 -> 0 | K16: =IF(J16>0,(G16-J16)/J16," ")
A17: 7062 | C17: Travaux pour tiers non associés | G17: =Temp!C19 -> 0 | J17: =Temp!D19 -> 0 | K17: =IF(J17>0,(G17-J17)/J17," ")
A18: 70614-70618 | C18: Autres travaux | G18: =Temp!C20 -> 185765.2 | J18: =Temp!D20 -> 145915.38 | K18: =IF(J18>0,(G18-J18)/J18," ") -> 0.27310226
A19: 703+708 | B19: Produits d'activités annexes | H19: =Temp!C21 -> 8963.38 | J19: =Temp!D21 -> 27354 | K19: =IF(J19>0,(H19-J19)/J19," ") -> -0.67231922
A20: 7084 | C20: Mise à disposition de personnel | G20: =Temp!C22 -> 0 | J20: =Temp!D22 -> 5351 | K20: =IF(J20>0,(G20-J20)/J20," ") -> -1
C21: Autres | G21: =H19-G20 -> 8963.38 | J21: =J19-J20 -> 22003 | K21: =IF(J21>0,(G21-J21)/J21," ") -> -0.59262919
A22: 707 | B22: Vente de marchandises dans la limite des 5% du CA | H22: =Temp!C90 -> 0 | J22: =Temp!D90 -> 0 | K22: =IF(J22>0,(G22-J22)/J22," ")
C24: MONTANT NET DU CHIFFRE D'AFFAIRES | H24: =pdt_act_annexe_N+H13+H22 -> 562308.95 | J24: =J19+J13+J22 -> 500655.03 | K24: =IF(J24>0,(H24-J24)/J24," ") -> 0.12314651
B26: Production stockée
A27: 7134 | C27: Activité de services | H27: =Temp!C23 -> 0 | J27: =Temp!D23 -> 0
A28: 72 | B28: Production immobilisée | H28: =Temp!C24 -> 0 | J28: =Temp!D24 -> 0 | K28: =IF(J28>0,(G28-J28)/J28," ")
A29: 74 | B29: Subventions d'exploitation | H29: =Temp!C25 -> 8433.84 | J29: =Temp!D25 -> 790.39 | K29: =IF(J29>0,(H29-J29)/J29," ") -> 9.6704791
A30: 747 | C30: Dont Quote-part des subventions d'investissement virées au résultat de l'exercice | G30: =Temp!C26 -> 0
A31: 757 | B31: Reventes d'immo | H31: =Temp!C30 -> 32500 | J31: =Temp!D30 -> 0 | K31: =IF(J31>0,(H31-J31)/J31," ")
A32: 781+791+7581 | B32: Reprises sur dépréciations, provisions (et amortissements), transferts de charges | H32: =Temp!C27+Temp!C32 -> 3569.57 | J32: =Temp!D27+Temp!D32 -> 0 | K32: =IF(J32>0,(H32-J32)/J32," ")
A33: 781 | C33: Reprises sur provisions | G33: =Temp!C28 -> 0 | J33: =Temp!D28 -> 0 | K33: =IF(J33>0,(G33-J33)/J33," ")
A34: 791+7581 | C34: Transfert de charges & remboursement d'assurances | G34: =Temp!C29+Temp!C32 -> 3569.57 | J34: =Temp!D29+Temp!D32 -> 0 | K34: =IF(J34>0,(G34-J34)/J34," ")
A35: 75 | B35: Autres produits | H35: =Temp!C31 -> 0.28 | J35: =Temp!D31 -> 0 | K35: =IF(J35>0,(H35-J35)/J35," ")
C36: TOTAL PRODUITS D'EXPLOITATION (I) | H36: =H35+repris_prov_N+subv_exploit_N+prod_immo_N+H27+CA_N+H31 -> 606812.64 | J36: =J35+J32+J29+J28+J27+J24+J31 -> 501445.42 | K36: =IF(J36>0,(H36-J36)/J36," ") -> 0.210127
A37: CHARGES D'EXPLOITATION | K37: =IF(J37>0,(G37-J37)/J37," ")
A39: 602 | B39: Achats de matières consommables et emballages | H39: =Temp!C33 -> 133398.96 | J39: =Temp!D33 -> 105187.06 | K39: =IF(J39>0,(H39-J39)/J39," ") -> 0.26820694
A40: 60211+60223 | C40: Lubrifiants, pièces détachées | G40: =Temp!C34 -> 60305.53 | J40: =Temp!D34 -> 40577.27 | K40: =IF(J40>0,(G40-J40)/J40," ") -> 0.48618993
A41: 60212 | C41: Carburants | G41: =Temp!C35 -> 65706.47 | J41: =Temp!D35 -> 60398.9 | K41: =IF(J41>0,(G41-J41)/J41," ") -> 0.087875276
A42: 60213 | C42: Matières incorporées au service | G42: =Temp!C36 -> 7386.96 | J42: =Temp!D36 -> 3706.92 | K42: =IF(J42>0,(G42-J42)/J42," ") -> 0.9927487
C43: Autres | G43: =H39-G40-G41-G42 -> -8.1854523e-12 | J43: =J39-J40-J41-J42 -> 503.97 | K43: =IF(J43>0,(G43-J43)/J43," ") -> -1
A44: 6032 | B44: Variations de stock | H44: =Temp!C37 -> 0 | J44: =Temp!D37 -> 2908.06 | K44: =IF(J44>0,(H44-J44)/J44," ") -> -1
A45: 607 | B45: Achats pour revente de marchandises | H45: =Temp!C89 -> 0 | J45: =Temp!D89 -> 0 | K45: =IF(J45>0,(H45-J45)/J45," ")
A46: 60x | B46: Autres achats | H46: =Temp!C38 -> 39600 | J46: =Temp!D38 -> 29241.84 | K46: =IF(J46>0,(H46-J46)/J46," ") -> 0.35422395
A47: 604 | C47: Sous-traitance | G47: =Temp!C39 -> 31710.4 | J47: =Temp!D39 -> 25043.22 | K47: =IF(J47>0,(G47-J47)/J47," ") -> 0.26622695
A48: 61+62 | B48: Charges externes | H48: =Temp!C40 -> 94569.91 | J48: =Temp!D40 -> 107236.58 | K48: =IF(J48>0,(H48-J48)/J48," ") -> -0.11811893
A49: 612-614 | C49: Locations | G49: =Temp!C41 -> 18400 | J49: =Temp!D41 -> 24980 | K49: =IF(J49>0,(G49-J49)/J49," ") -> -0.26341073
A50: 615 | C50: Entretien réparation | G50: =Temp!C42 -> 33908.29 | J50: =Temp!D42 -> 37820.07 | K50: =IF(J50>0,(G50-J50)/J50," ") -> -0.10343133
A51: 621 | C51: Personnel extérieur | G51: =Temp!C43 -> 14400 | J51: =Temp!D43 -> 22670 | K51: =IF(J51>0,(G51-J51)/J51," ") -> -0.36479929
A52: 622 | C52: Honoraires (compta, gestion...) | G52: =Temp!C44 -> 4534.88 | J52: =Temp!D44 -> 4661.87 | K52: =IF(J52>0,(G52-J52)/J52," ") -> -0.027240142
A53: 626 | C53: PTT, télécommunications | G53: =Temp!C45 -> 1754.58 | J53: =Temp!D45 -> 1034.75 | K53: =IF(J53>0,(G53-J53)/J53," ") -> 0.69565596
A54: 61+62 | C54: Autres charges externes | G54: =Temp!C46 -> 21572.16 | J54: =Temp!D46 -> 16069.89 | K54: =IF(J54>0,(G54-J54)/J54," ") -> 0.34239625
A55: 616 | C55: Assurances | G55: =Temp!C47 -> 12460 | J55: =Temp!D47 -> 10846.05 | K55: =IF(J55>0,(G55-J55)/J55," ") -> 0.14880533
A56: 628 | C56: Cotisations fédératives | G56: =Temp!C48 -> 3851.51 | J56: =Temp!D48 -> 3174.07 | K56: =IF(J56>0,(G56-J56)/J56," ") -> 0.21342945
A57: 618 | C57: Abonnements | G57: =Temp!C49 -> 1072.5 | J57: =Temp!D49 -> 999 | K57: =IF(J57>0,(G57-J57)/J57," ") -> 0.073573574
C58: Autres | G58: =G54-G55-G56-G57 -> 4188.15 | J58: =J54-J55-J56-J57 -> 1050.77 | K58: =IF(J58>0,(G58-J58)/J58," ") -> 2.9857914
A59: 63 | B59: Impôts, taxes et versements assimilés | H59: =Temp!C50 -> 0 | J59: =Temp!D50 -> 0 | K59: =IF(J59>0,(H59-J59)/J59," ")
A60: 641 | B60: Salaires et traitements | H60: =Temp!C51 -> 55380.12 | J60: =Temp!D51 -> 27989.04 | K60: =IF(J60>0,(H60-J60)/J60," ") -> 0.97863592
A61: 64111 | C61: Conduite | G61: =Temp!C52 -> 0 | J61: =Temp!D52 -> 0 | K61: =IF(J61>0,(G61-J61)/J61," ")
A62: 64112 | C62: Entretien | G62: =Temp!C53 -> 0 | J62: =Temp!D53 -> 0 | K62: =IF(J62>0,(G62-J62)/J62," ")
A63: 645-648 | B63: Charges sociales | H63: =Temp!C54 -> 12348.73 | J63: =Temp!D54 -> 4416.71 | K63: =IF(J63>0,(H63-J63)/J63," ") -> 1.7959114
B64: Dotations aux amortissements et aux provisions | K64: =IF(J64>0,(H64-J64)/J64," ")
A65: 6811+6812 | C65: Sur immobilisations : dotations aux amortissements | H65: =Temp!C55 -> 0 | J65: =Temp!D55 -> 187408.12 | K65: =IF(J65>0,(H65-J65)/J65," ") -> -1
A66: 6816 | C66: Sur immobilisations : dotations aux provisions | H66: =Temp!C56 -> 0 | J66: =Temp!D56 -> 0 | K66: =IF(J66>0,(H66-J66)/J66," ")
A67: 6817 | C67: Sur actif circulant : dotations aux dépréciations | H67: =Temp!C57 -> 0 | J67: =Temp!D57 -> 79.55 | K67: =IF(J67>0,(H67-J67)/J67," ") -> -1
A68: 6815 | C68: Pour risques et charges : dotations aux provisions | H68: =Temp!C58 -> 0 | J68: =Temp!D58 -> 0 | K68: =IF(J68>0,(H68-J68)/J68," ")
A69: 657 | B69: VNC d'immobilisation | H69: =Temp!C59 -> 0 | J69: =Temp!D59 -> 0 | K69: =IF(J69>0,(H69-J69)/J69," ")
A70: 65 | B70: Autres charges | H70: =Temp!C60 -> 14800 | J70: =Temp!D60 -> 13950.34 | K70: =IF(J70>0,(H70-J70)/J70," ") -> 0.060906042
A71: 653 | C71: Indemnités administrateurs | G71: =Temp!C61 -> 12750 | J71: =Temp!D61 -> 11900 | K71: =IF(J71>0,(G71-J71)/J71," ") -> 0.071428571
C72: Autres | G72: =H70-G71 -> 2050 | J72: =J70-J71 -> 2050.34 | K72: =IF(J72>0,(G72-J72)/J72," ") -> -0.00016582616
C73: TOTAL CHARGES D'EXPLOITATION (II) | H73: =indemn_adm_N+SUM(H65:H68)+salaires_N+taxes_N+tot_achat_N+aut_achat_N+sous_trait_N+lub_piece_N+H63+H45+H69 -> 350097.72 | J73: =J70+SUM(J65:J68)+J60+J59+J48+J46+J44+J39+J63+J45+J69 -> 478417.3 | K73: =IF(J73>0,(H73-J73)/J73," ") -> -0.26821685
A74: 1) RESULTAT D'EXPLOITATION (I - II) | H74: =tot_prod_expl_N-tot_ch_exploit_n -> 256714.92 | J74: =J36-J73 -> 23028.12 | K74: =IF(J74>0,(H74-J74)/J74," ") -> 10.147889
A75: 757-657 | G75: Dont plus-value sur cession d’immobilisations | H75: =Temp!C62 -> 32500 | J75: =Temp!D62 -> 0 | K75: =IF(J75>0,(H75-J75)/J75," ")
A77: RESULTAT FINANCIER | H77: TOTAL N | J77: ANNEE N-1 | K77: Var.n/n-1
A78: RESULTAT D'EXPLOITATION | H78: =res_exploit_N -> 256714.92 | J78: =J74 -> 23028.12 | K78: =K74 -> 10.147889
B80: Quotes-parts de résultat sur opérations faites en commun | K80: =IF(J80>0,(H81-J80)/J80," ")
A81: 755 | C81: Bénéfice ou perte transféré | H81: =Temp!C63 -> 0 | J81: =Temp!D63 -> 0 | K81: =IF(J81>0,(H81-J81)/J81," ")
A82: 655 | C82: Perte ou bénéfice transféré | H82: =Temp!C64 -> 0 | J82: =Temp!D64 -> 0 | K82: =IF(J82>0,(H82-J82)/J82," ")
A83: PRODUITS FINANCIERS | K83: =IF(J83>0,(H85-J83)/J83," ")
A85: 7612 | C85: De participation à des organismes coopératifs agricoles | H85: =Temp!C65 -> 0 | J85: =Temp!D65 -> 0 | K85: =IF(J85>0,(H85-J85)/J85," ")
A86: 7611+7616 | C86: D'autres participations | H86: =Temp!C66 -> 0 | J86: =Temp!D66 -> 0 | K86: =IF(J86>0,(H86-J86)/J86," ")
A87: 762 | C87: D'autres valeurs mobilières et créances de l'actif immobilisé | H87: =Temp!C67 -> 68.86 | J87: =Temp!D67 -> 67.07 | K87: =IF(J87>0,(H87-J87)/J87," ") -> 0.026688534
A88: 763+-765+768 | C88: Autres intérêts et produits assimilés | H88: =Temp!C68 -> 2592.5 | J88: =Temp!D68 -> 1124.33 | K88: =IF(J88>0,(H88-J88)/J88," ") -> 1.3058177
A89: 786+796 | C89: Reprises sur provisions et transfert de charges | H89: =Temp!C69 -> 0 | J89: =Temp!D69 -> 0 | K89: =IF(J89>0,(H89-J89)/J89," ")
A90: 766 | C90: Différences positives de change | H90: =Temp!C70 -> 0 | J90: =Temp!D70 -> 0 | K90: =IF(J90>0,(H90-J90)/J90," ")
A91: 767 | C91: Produits nets sur cessions de valeurs mobilières de placement | H91: =Temp!C71 -> 0 | J91: =Temp!D71 -> 0 | K91: =IF(J91>0,(H91-J91)/J91," ")
C92: TOTAL PRODUITS FINANCIERS (III) | H92: =SUM(H85:H91) -> 2661.36 | J92: =SUM(J85:J91) -> 1191.4 | K92: =IF(J92>0,(H92-J92)/J92," ") -> 1.233809
A93: CHARGE FINANCIERES
A95: 686 | C95: Dotations aux amortissements, dépréciations et provisions | H95: =Temp!C72 -> 0 | J95: =Temp!D72 -> 0 | K95: =IF(J95>0,(H95-J95)/J95," ")
A96: 66 | C96: Intérêts et charges assimilées | H96: =Temp!C73 -> 25126.49 | J96: =Temp!D73 -> 25599.09 | K96: =IF(J96>0,(H96-J96)/J96," ") -> -0.018461594
A97: 6618 | C97: Agios (fournisseurs et O.C.) | G97: =Temp!C74 -> 0 | J97: =Temp!D74 -> 0 | K97: =IF(J97>0,(G97-J97)/J97," ")
A98: 661 | C98: Intérêts bancaires et autres | G98: =Temp!C75 -> 19138.11 | J98: =Temp!D75 -> 19815.67 | K98: =IF(J98>0,(G98-J98)/J98," ") -> -0.034193141
C99: Autres | G99: =H96-G97-G98 -> 5988.38 | J99: =J96-J97-J98 -> 5783.42 | K99: =IF(J99>0,(G99-J99)/J99," ") -> 0.035439238
A100: 666 | C100: Différences négatives de change | H100: =Temp!C76 -> 0 | J100: =Temp!D76 -> 0 | K100: =IF(J100>0,(H100-J100)/J100," ")
A101: 667 | C101: Charges nettes sur cessions de valeurs mobilières de placement | H101: =Temp!C77 -> 0 | J101: =Temp!D77 -> 0 | K101: =IF(J101>0,(H101-J101)/J101," ")
C102: TOTAL CHARGES FINANCIERES (IV) | H102: =H100+H101+interet_banque_N+agios_four_N -> 25126.49 | J102: =J95+J96+J100+J101 -> 25599.09 | K102: =IF(J102>0,(H102-J102)/J102," ") -> -0.018461594
A103: 2) RESULTAT FINANCIER (III - IV) | H103: =Tot_prod_fi_n-tot_ch_fi_N -> -22465.13 | J103: =J92-J102 -> -24407.69 | K103: =IF(J103>0,(H103-J103)/J103," ")
A105: 3) RESULTAT COURANT (I - II + III - IV) | H105: =H78+prod_val_mob_N-H82+Tot_prod_fi_n-tot_ch_fi_N -> 234249.79 | J105: =J78+J80-J81+J92-J102 -> -1379.57 | K105: =IF(J105>0,(H105-J105)/J105," ")
A107: PRODUITS EXCEPTIONNELS
A109: 77 | C109: Sur opération de gestion | H109: =Temp!C78 -> 0 | J109: =Temp!D78 -> 1886.11 | K109: =IF(J109>0,(H109-J109)/J109," ") -> -1
A110: 775+777 | C110: Sur opération en capital (dont revente) | H110: =Temp!C79 -> 118500 | J110: =Temp!D79 -> 12000 | K110: =IF(J110>0,(H110-J110)/J110," ") -> 8.875
A111: 777 | C111: Quote part des subventions d'investissement | G111: =Temp!C80 -> 0
A112: 787+797 | C112: Reprises sur dépréciations et provisions, transferts de charges | H112: =Temp!C81 -> 0 | J112: =Temp!D81 -> 0 | K112: =IF(J112>0,(H112-J112)/J112," ")
C113: TOTAL PRODUITS EXCEPTIONNELS (V) | H113: =prod_capital_N+trans_ch_except_N+aut_prod_except_N -> 118500 | J113: =SUM(J109:J112) -> 13886.11 | K113: =IF(J113>0,(H113-J113)/J113," ") -> 7.5337074
A114: CHARGES EXCEPTIONNELLES
A116: 67 | C116: Sur opération de gestion | H116: =Temp!C82 -> 19.88 | J116: =Temp!D82 -> 384.42 | K116: =IF(J116>0,(H116-J116)/J116," ") -> -0.94828573
...
